wagon.py
wagon-0.6.0.dist-info/DESCRIPTION.rst
wagon-0.6.0.dist-info/LICENSE.txt
wagon-0.6.0.dist-info/METADATA
wagon-0.6.0.dist-info/RECORD
wagon-0.6.0.dist-info/WHEEL
wagon-0.6.0.dist-info/entry_points.txt
wagon-0.6.0.dist-info/metadata.json
wagon-0.6.0.dist-info/top_level.txt
