Metadata-Version: 2.0
Name: wagon
Version: 0.6.0
Summary: Creates Python Wheel based archives with dependencies
Home-page: https://github.com/cloudify-cosmo/wagon
Author: Gigaspaces
Author-email: cosmo-admin@gigaspaces.com
License: Apache 2.0
Platform: All
Classifier: Development Status :: 4 - Beta
Classifier: Programming Language :: Python
Classifier: Programming Language :: Python :: 2.6
Classifier: Programming Language :: Python :: 2.7
Classifier: Programming Language :: Python :: 3
Classifier: Programming Language :: Python :: 3.3
Classifier: Programming Language :: Python :: 3.4
Classifier: Programming Language :: Python :: 3.5
Classifier: Programming Language :: Python :: 3.6
Classifier: Natural Language :: English
Classifier: Environment :: Console
Classifier: Intended Audience :: Developers
Classifier: Intended Audience :: Information Technology
Classifier: Intended Audience :: System Administrators
Classifier: License :: OSI Approved :: Apache Software License
Classifier: Operating System :: MacOS :: MacOS X
Classifier: Operating System :: POSIX :: Linux
Classifier: Operating System :: Microsoft
Classifier: Topic :: Software Development :: Libraries :: Python Modules
Requires-Dist: wheel (>=0.24.0)
Provides-Extra: dist
Requires-Dist: distro (>=0.6.0); extra == 'dist'
Provides-Extra: venv
Requires-Dist: virtualenv (>=12.1); extra == 'venv'
